pynubank/__init__.py
pynubank/auth_mode.py
pynubank/cli.py
pynubank/exception.py
pynubank/nubank.py
pynubank/queries/account_balance.gql
pynubank/queries/account_feed.gql
pynubank/queries/account_feed_paginated.gql
pynubank/queries/account_id.gql
pynubank/queries/account_investments.gql
pynubank/queries/account_investments_yield.gql
pynubank/queries/account_savings.gql
pynubank/queries/create_boleto.gql
pynubank/queries/create_money_request.gql
pynubank/queries/create_pix_money_request.gql
pynubank/queries/get_pix_keys.gql
pynubank/queries/pix_receipt_screen.gql
pynubank/utils/__init__.py
pynubank/utils/certificate_generator.py
pynubank/utils/discovery.py
pynubank/utils/graphql.py
pynubank/utils/http.py
pynubank/utils/mock_http.py
pynubank/utils/parsing.py
pynubank/utils/mocked_responses/__init__.py
pynubank/utils/mocked_responses/account.json
pynubank/utils/mocked_responses/account_balance.json
pynubank/utils/mocked_responses/account_feed.json
pynubank/utils/mocked_responses/account_feed_paginated.json
pynubank/utils/mocked_responses/account_investments.json
pynubank/utils/mocked_responses/account_investments_yield.json
pynubank/utils/mocked_responses/account_savings.json
pynubank/utils/mocked_responses/bills.json
pynubank/utils/mocked_responses/bills_summary.json
pynubank/utils/mocked_responses/boleto_create.json
pynubank/utils/mocked_responses/card_statement_detail.json
pynubank/utils/mocked_responses/customer.json
pynubank/utils/mocked_responses/discovery_api.json
pynubank/utils/mocked_responses/discovery_app.json
pynubank/utils/mocked_responses/discovery_login.json
pynubank/utils/mocked_responses/discovery_login_alternative.json
pynubank/utils/mocked_responses/money.json
pynubank/utils/mocked_responses/pix_keys.json
pynubank/utils/mocked_responses/pix_money_request.json
pynubank/utils/mocked_responses/pix_receipt_screen.json
pynubank/utils/mocked_responses/pix_receipt_screen_not_found.json
pynubankasync-2.25.1.dist-info/LICENSE
pynubankasync-2.25.1.dist-info/METADATA
pynubankasync-2.25.1.dist-info/WHEEL
pynubankasync-2.25.1.dist-info/entry_points.txt
pynubankasync-2.25.1.dist-info/top_level.txt
pynubankasync-2.25.1.dist-info/RECORD
