Metadata-Version: 2.1
Name: pynubankasync
Version: 2.25.1
Home-page: https://github.com/humbertogontijo/pynubankasync
Author: André Roggeri Campos
Author-email: a.roggeri.c@gmail.com
License: MIT
Classifier: Programming Language :: Python
Classifier: Programming Language :: Python :: 3.7
Classifier: Programming Language :: Python :: 3.8
Classifier: Programming Language :: Python :: 3.9
Classifier: Programming Language :: Python :: 3.10
License-File: LICENSE
Requires-Dist: qrcode (==7.3.1)
Requires-Dist: pyOpenSSL (==23.2.0)
Requires-Dist: colorama (==0.4.3)
Requires-Dist: Deprecated (==1.2.14)
Requires-Dist: setuptools (~=65.5.1)
Requires-Dist: pynubank (~=2.25.0)
Requires-Dist: httpx (~=0.24.1)
Requires-Dist: cryptography (~=41.0.3)
Requires-Dist: httpx-pkcs12 (~=1.0.3)
